[{"s": "imitatsiya-cherepitsy-dlya-kryshi", "t": "Имитация черепицы: виды, монтаж и критерии выбора", "i": "🏗️", "c": "vidy-krovli"}, {"s": "imitatsiya-brusa-na-karkasnom-dome", "t": "Имитация бруса на каркасном доме: выбор и монтаж", "i": "🧱", "c": "fasad-i-sajding"}, {"s": "imitatsiya-cherepitsy", "t": "Имитация черепицы: виды, выбор и монтаж своими руками", "i": "🏗️", "c": "vidy-krovli"}, {"s": "imitatsiya-faltsevoj-krovli-proflist", "t": "Имитация фальца профлистом: монтаж и выбор профиля", "i": "🏗️", "c": "vidy-krovli"}, {"s": "imitatsiya-brusa-plyusy-i-minusy", "t": "Имитация бруса: плюсы и минусы, сравнение с сайдингом и блок-хаусом", "i": "🧱", "c": "fasad-i-sajding"}, {"s": "imitatsiya-brusa-snaruzhi-doma", "t": "Имитация бруса снаружи дома: выбор, монтаж и ошибки", "i": "🧱", "c": "fasad-i-sajding"}]