[{"s": "shag-stropilnoj-sistemy", "t": "Шаг стропильной системы: расчет и нормы", "i": "📐", "c": "stropilnaya-sistema"}, {"s": "shirina-frontona", "t": "Ширина фронтона: расчет, устройство и ошибки", "i": "📐", "c": "stropilnaya-sistema"}, {"s": "shokoladnyj-tsvet-kryshi", "t": "Шоколадный цвет крыши: выбор, сочетание с фасадом и практичность", "i": "🏗️", "c": "vidy-krovli"}, {"s": "shpaklevanie-po-steklokholstu", "t": "Шпаклевка по стеклохолсту: технология, выбор смеси и финиш", "i": "🎨", "c": "vnutrennyaya-otdelka"}, {"s": "shpaklevka-po-gidroizolyatsii", "t": "Шпаклевка по гидроизоляции: выбор материалов и технология", "i": "💧", "c": "gidroizolyatsiya"}, {"s": "shprengelnaya-sistema-usileniya-balok", "t": "Шпренгельная система усиления балок: принципы и монтаж", "i": "📐", "c": "stropilnaya-sistema"}, {"s": "shtory-dlya-treugolnogo-okna-mansardy", "t": "Шторы для треугольного окна мансарды: виды и способы крепления", "i": "🎨", "c": "vnutrennyaya-otdelka"}, {"s": "shtory-na-okna-trapetsievidnoj-formy", "t": "Шторы на трапециевидные окна: выбор, крепление и дизайн", "i": "🎨", "c": "vnutrennyaya-otdelka"}, {"s": "shumoizolyatsiya-iz-vojloka", "t": "Шумоизоляция из войлока: применение, монтаж и эффективность", "i": "🎨", "c": "vnutrennyaya-otdelka"}, {"s": "shag-obreshetki-pod-keramicheskuyu-cherepitsu", "t": "Шаг обрешетки под керамическую черепицу: точный расчет и монтаж", "i": "🔨", "c": "montazh-krovli"}, {"s": "shirina-mauerlata", "t": "Ширина мауэрлата: размеры, расчет, выбор сечения бруса", "i": "📐", "c": "stropilnaya-sistema"}, {"s": "shumoizolyatsiya-shumanet-100", "t": "Шумоизоляция Шуманет 100: характеристики и схема монтажа", "i": "🎨", "c": "vnutrennyaya-otdelka"}, {"s": "shag-mezhdu-stropilami-dvukhskatnoj-kryshi", "t": "Шаг между стропилами двухскатной крыши: расчет и нормы", "i": "📐", "c": "stropilnaya-sistema"}, {"s": "shag-obreshetki-eto", "t": "Шаг обрешетки под кровлю: нормы, расчет и монтаж", "i": "📐", "c": "stropilnaya-sistema"}, {"s": "shag-stropil-odnoskatnoj-kryshi-pod-profnastil", "t": "Шаг стропил под профнастил: расчет и нормы для односкатной крыши", "i": "📐", "c": "stropilnaya-sistema"}, {"s": "shtaketnik-metallicheskij-dlya-zabora-razmery-po-vysote", "t": "Металлический штакетник: размеры высоты для забора и выбор", "i": "🚧", "c": "zabory-i-ograzhdeniya"}, {"s": "shag-stropil-dvukhskatnoj-kryshi", "t": "Шаг стропил двухскатной крыши: расчет и нормы", "i": "📐", "c": "stropilnaya-sistema"}, {"s": "shpatlevka-dlya-shvov", "t": "Шпатлевка для швов: выбор, нанесение и ошибки", "i": "🎨", "c": "vnutrennyaya-otdelka"}, {"s": "shumoizolyatsiya-kryshi-doma-iz-profnastila", "t": "Шумоизоляция крыши из профнастила: материалы и монтаж", "i": "🌡️", "c": "uteplenie-doma"}, {"s": "shirina-ruberoida-v-rulone", "t": "Ширина рубероида в рулоне: размеры по ГОСТ и выбор", "i": "💧", "c": "gidroizolyatsiya"}, {"s": "shprengelnaya-ferma-eto", "t": "Шпренгельная ферма: устройство, расчет и применение в кровле", "i": "📐", "c": "stropilnaya-sistema"}, {"s": "shirina-metallocherepitsy-monterrej", "t": "Ширина металлочерепицы Монтеррей: размеры, полезная и габаритная", "i": "🏗️", "c": "vidy-krovli"}, {"s": "shirina-nesushchej-steny-iz-kirpicha", "t": "Ширина несущей стены из кирпича: нормы и расчет толщины", "i": "🧮", "c": "raschety-i-smety"}, {"s": "shirina-parapeta-na-ploskoj-krovle", "t": "Ширина парапета на плоской кровле: нормы и требования", "i": "🔨", "c": "montazh-krovli"}, {"s": "shpaklevka-vmesto-oboev", "t": "Шпаклевка вместо обоев: плюсы, минусы и технология нанесения", "i": "🎨", "c": "vnutrennyaya-otdelka"}, {"s": "shpatlevka-pod-steklokholst", "t": "Шпатлевка под стеклохолст: нужно ли шпаклевать и как", "i": "🎨", "c": "vnutrennyaya-otdelka"}, {"s": "shtory-na-skoshennye-okna-v-mansarde-v-derevyannom-dome", "t": "Шторы на скошенные окна в мансарде: выбор и монтаж в деревянном доме", "i": "🎨", "c": "vnutrennyaya-otdelka"}, {"s": "shumoizolyatsiya-kryshi-doma", "t": "Шумоизоляция крыши дома: материалы и технология монтажа", "i": "🌡️", "c": "uteplenie-doma"}, {"s": "shumoizolyatsiya-sendvich-panelej", "t": "Шумоизоляция сэндвич-панелей: материалы и монтаж", "i": "🌡️", "c": "uteplenie-doma"}, {"s": "shag-obreshetki-pod-profnastil-dlya-odnoskatnoj-kryshi", "t": "Шаг обрешетки под профнастил для односкатной крыши: расчет и монтаж", "i": "🔨", "c": "montazh-krovli"}, {"s": "shtukaturka-uteplitelya-po-setke", "t": "Штукатурка утеплителя по сетке: пошаговая технология и материалы", "i": "🌡️", "c": "uteplenie-doma"}, {"s": "shag-obreshetki-pod-metallocherepitsu-dlya-kryshi", "t": "Шаг обрешетки под металлочерепицу: точный расчет", "i": "🔨", "c": "montazh-krovli"}, {"s": "shirina-uteplitelya-dlya-pola", "t": "Ширина утеплителя для пола: размеры, выбор и монтаж", "i": "🌡️", "c": "uteplenie-doma"}, {"s": "shifer-ili-profnastil-chto-luchshe-dlya-kryshi", "t": "Шифер или профнастил: что лучше для крыши и как выбрать", "i": "🏗️", "c": "vidy-krovli"}, {"s": "shirina-profnastila-dlya-kryshi-standart-razmery", "t": "Ширина профнастила для крыши: стандартные размеры и расчет", "i": "🏗️", "c": "vidy-krovli"}, {"s": "shag-krepleniya-metallocherepitsy-samorezami-skhema", "t": "Шаг крепления металлочерепицы саморезами: схема и правила", "i": "🔨", "c": "montazh-krovli"}, {"s": "shag-lag-dlya-pola-iz-dosok-tablitsa", "t": "Шаг лаг для пола из досок: таблица и расчет сечения", "i": "🎨", "c": "vnutrennyaya-otdelka"}, {"s": "shag-obreshetki-dlya-myagkoj-krovli", "t": "Шаг обрешетки под мягкую кровлю: нормы, расчеты и ошибки", "i": "🔨", "c": "montazh-krovli"}, {"s": "shirina-uteplitelya", "t": "Ширина утеплителя: выбор, монтаж и расчёт материалов", "i": "🌡️", "c": "uteplenie-doma"}, {"s": "shtukaturka-uteplitelya", "t": "Штукатурка утеплителя: технология нанесения и выбор смеси", "i": "🧱", "c": "fasad-i-sajding"}, {"s": "shag-stropil-pod-metallocherepitsu", "t": "Шаг стропил под металлочерепицу: расчет и нормы монтажа", "i": "📐", "c": "stropilnaya-sistema"}, {"s": "shatrovaya-krysha", "t": "Шатровая крыша: устройство, расчет и монтаж своими руками", "i": "🏗️", "c": "vidy-krovli"}, {"s": "shifer-andulinovyj", "t": "Андулиновый шифер: характеристики, плюсы, минусы и монтаж", "i": "🏗️", "c": "vidy-krovli"}, {"s": "shpaklevanie-steklokholsta-pod-pokrasku", "t": "Шпаклевание стеклохолста под покраску: технология и материалы", "i": "🎨", "c": "vnutrennyaya-otdelka"}, {"s": "shpatlevanie-pod-pokrasku", "t": "Шпатлевание стен под покраску: инструкция и выбор материалов", "i": "🎨", "c": "vnutrennyaya-otdelka"}, {"s": "shtukaturka-kamennoj-vaty", "t": "Технология штукатурки каменной ваты: пошаговая инструкция", "i": "🌡️", "c": "uteplenie-doma"}, {"s": "shatrovye-konstruktsii", "t": "Шатровые крыши: устройство, расчет и монтаж своими руками", "i": "📐", "c": "stropilnaya-sistema"}, {"s": "shirina-uteplitelya-dlya-karkasnogo-doma", "t": "Ширина утеплителя для каркасного дома: выбор и монтаж", "i": "🌡️", "c": "uteplenie-doma"}, {"s": "shtory-na-skoshennyj-potolok", "t": "Шторы на скошенный потолок: выбор, крепление и монтаж", "i": "🎨", "c": "vnutrennyaya-otdelka"}, {"s": "shtukaturka-dlya-minvaty", "t": "Штукатурка для минваты: выбор материала и технология", "i": "🌡️", "c": "uteplenie-doma"}, {"s": "shag-kontrobreshetki", "t": "Шаг контробрешетки под кровлю: нормы, размеры и ошибки", "i": "📐", "c": "stropilnaya-sistema"}, {"s": "shirina-proflista-krovelnogo", "t": "Ширина профлиста кровельного: полная, полезная и рабочая", "i": "🏗️", "c": "vidy-krovli"}, {"s": "shirina-rulona-paroizolyatsii", "t": "Ширина рулона пароизоляции: размеры, выбор, стандарты", "i": "🌡️", "c": "uteplenie-doma"}, {"s": "shag-vodostochnykh-voronok", "t": "Шаг водосточных воронок: расчет расстояния и монтаж", "i": "🔨", "c": "montazh-krovli"}, {"s": "shagovaya-obreshetka-chto-eto", "t": "Шаговая обрешетка крыши: что это, расчет и монтаж", "i": "📐", "c": "stropilnaya-sistema"}, {"s": "shatrovaya-krysha-skhema", "t": "Шатровая крыша: схема стропильной системы и расчет", "i": "📐", "c": "stropilnaya-sistema"}, {"s": "shinglas-kantri", "t": "Гибкая черепица Shinglas Кантри: монтаж и характеристики", "i": "🏗️", "c": "vidy-krovli"}, {"s": "shirina-kirpichnykh-sten", "t": "Ширина кирпичных стен: стандарты, виды кладки и расчет", "i": "🧱", "c": "fasad-i-sajding"}, {"s": "shirina-rulonnogo-uteplitelya", "t": "Ширина рулонного утеплителя: выбор и размеры", "i": "🌡️", "c": "uteplenie-doma"}, {"s": "shpilki-dlya-stropilnoj-sistemy", "t": "Шпильки для стропильной системы: размеры, монтаж, расчет", "i": "📐", "c": "stropilnaya-sistema"}, {"s": "shtory-so-skosom", "t": "Шторы со скосом: выбор, раскрой и монтаж на асимметричные окна", "i": "🎨", "c": "vnutrennyaya-otdelka"}, {"s": "shtukaturka-po-mineralnoj-vate", "t": "Штукатурка по минеральной вате: технология мокрого фасада", "i": "🧱", "c": "fasad-i-sajding"}, {"s": "shumanit-100-zvukoizolyatsiya", "t": "Шуманит 100: характеристики, применение и монтаж звукоизоляции", "i": "🎨", "c": "vnutrennyaya-otdelka"}, {"s": "shag-ustanovki-kronshtejnov-dlya-vodostochnykh-zhelobov", "t": "Шаг установки кронштейнов для водосточных желобов: нормы и расчет", "i": "🔨", "c": "montazh-krovli"}, {"s": "shumoizolyatsiya-dlya-profnastila", "t": "Шумоизоляция кровли из профнастила: материалы и монтаж", "i": "🌡️", "c": "uteplenie-doma"}, {"s": "shag-lag-dlya-terrasnoj-doski", "t": "Шаг лаг для террасной доски: расчеты и нормы монтажа", "i": "🧖", "c": "banya-i-terrasa"}, {"s": "shag-mezhdu-stropilami-dvukhskatnoj-kryshi-pod-proflist", "t": "Шаг стропил под профлист: точный расчет и нормы", "i": "📐", "c": "stropilnaya-sistema"}, {"s": "shurupy-dlya-sajdinga-po-derevyannomu-karkasu", "t": "Шурупы для сайдинга по дереву: выбор, размеры, монтаж", "i": "🧱", "c": "fasad-i-sajding"}, {"s": "shag-balok-pod-terrasnuyu-dosku", "t": "Шаг балок под террасную доску: нормы и расчет расстояния", "i": "🧖", "c": "banya-i-terrasa"}, {"s": "shag-stropil-dvuskatnoj-kryshi-pod-shifer", "t": "Шаг стропил под шифер: расчет и монтаж", "i": "📐", "c": "stropilnaya-sistema"}, {"s": "shirina-krovelnogo-proflista-dlya-kryshi-razmery", "t": "Ширина профлиста для кровли: полная, полезная и нахлест", "i": "🏗️", "c": "vidy-krovli"}, {"s": "shpl-panel", "t": "ШПЛ панель: описание, монтаж и характеристики плит", "i": "🎨", "c": "vnutrennyaya-otdelka"}, {"s": "shtory-na-mansardnye-okna-so-skoshennym-potolkom-v-derevyannyj-dom-foto-dizajn", "t": "Шторы на мансардные окна: дизайн и монтаж в деревянном доме", "i": "🎨", "c": "vnutrennyaya-otdelka"}, {"s": "shtukaturka-sten-iz-keramzitobetonnykh-blokov", "t": "Штукатурка стен из керамзитобетонных блоков: технология и материалы", "i": "🎨", "c": "vnutrennyaya-otdelka"}, {"s": "shtukaturka-sten-po-uteplitelyu-snaruzhi", "t": "Штукатурка стен по утеплителю снаружи: технология мокрого фасада", "i": "🧱", "c": "fasad-i-sajding"}, {"s": "shpaklevka-sten-pod-pokrasku-svoimi-rukami", "t": "Шпаклевка стен под покраску своими руками: пошаговая инструкция", "i": "🎨", "c": "vnutrennyaya-otdelka"}, {"s": "shtory-na-trapetsievidnoe-okno", "t": "Шторы на трапециевидное окно: выбор, замер и монтаж", "i": "🎨", "c": "vnutrennyaya-otdelka"}, {"s": "shtory-v-mansarde-so-skoshennym-potolkom-foto", "t": "Шторы в мансарде со скошенным потолком: фото, выбор и монтаж", "i": "🎨", "c": "vnutrennyaya-otdelka"}, {"s": "shifer-pod-cherepitsu", "t": "Шифер под черепицу: как уложить правильно и дешево", "i": "🏗️", "c": "vidy-krovli"}, {"s": "shipovidnaya-membrana", "t": "Шиповидная мембрана: назначение, применение и монтаж", "i": "💧", "c": "gidroizolyatsiya"}, {"s": "shtukaturka-na-minvatu", "t": "Штукатурка по минвате: технология и выбор материалов", "i": "🌡️", "c": "uteplenie-doma"}, {"s": "shag-obreshetki-krovli", "t": "Шаг обрешетки кровли: размеры и расчет под металлочерепицу", "i": "📐", "c": "stropilnaya-sistema"}, {"s": "shag-obreshetki-odnoskatnoj-kryshi", "t": "Шаг обрешетки односкатной крыши: расчет и монтаж", "i": "📐", "c": "stropilnaya-sistema"}, {"s": "shatrovaya-krysha-svoimi-rukami-poshagovo", "t": "Шатровая крыша своими руками: пошаговая инструкция", "i": "📐", "c": "stropilnaya-sistema"}, {"s": "shumoizolyatsiya-krovli-iz-profnastila-ot-dozhdya", "t": "Шумоизоляция кровли из профнастила от дождя", "i": "🔨", "c": "montazh-krovli"}, {"s": "shag-obreshetki-pod-metallosajding", "t": "Шаг обрешетки под металлосайдинг: нормы и инструкция", "i": "🧱", "c": "fasad-i-sajding"}, {"s": "shirina-sajdinga-dlya-naruzhnoj-otdelki-plastikovyj", "t": "Ширина пластикового сайдинга: размеры, выбор и монтаж", "i": "🧱", "c": "fasad-i-sajding"}, {"s": "shtukaturka-ili-oboi-chto-luchshe", "t": "Штукатурка или обои: сравнение и выбор отделки", "i": "🎨", "c": "vnutrennyaya-otdelka"}, {"s": "shumoizolyatsiya-kamennoj-vatoj", "t": "Шумоизоляция каменной ватой: технология и выбор материалов", "i": "🌡️", "c": "uteplenie-doma"}, {"s": "shag-obreshetki-dlya-ondulina", "t": "Шаг обрешетки под ондулин: точные размеры и монтаж", "i": "🔨", "c": "montazh-krovli"}, {"s": "shifer-ondulinovyj", "t": "Ондулиновый шифер: характеристики, монтаж и выбор", "i": "🏗️", "c": "vidy-krovli"}, {"s": "shumanet-kombi-i-gidro-otlichiya", "t": "Шуманет Комби и Гидро: отличия, выбор и применение", "i": "🎨", "c": "vnutrennyaya-otdelka"}, {"s": "shumoizolyatsiya-kryshi", "t": "Шумоизоляция крыши: материалы и технологии монтажа", "i": "🌡️", "c": "uteplenie-doma"}, {"s": "shag-mezhdu-stolbami-zabora", "t": "Оптимальный шаг столбов забора для разных материалов", "i": "🚧", "c": "zabory-i-ograzhdeniya"}, {"s": "shifer-na-kryshu-plyusy-i-minusy", "t": "Шифер на крышу: плюсы и минусы, выбор и монтаж", "i": "🏗️", "c": "vidy-krovli"}, {"s": "shtukaturka-tekhnonikol-302", "t": "Штукатурка Технониколь 302: свойства, монтаж и ошибки", "i": "🧱", "c": "fasad-i-sajding"}, {"s": "shag-obreshetki-dlya-metallocherepitsy-iz-100-doski", "t": "Шаг обрешетки для металлочерепицы из доски 100 мм", "i": "🔨", "c": "montazh-krovli"}, {"s": "shag-ustanovki-stropil-dvuskatnoj-kryshi", "t": "Шаг установки стропил двускатной крыши: нормы и расчет", "i": "📐", "c": "stropilnaya-sistema"}, {"s": "shpatlevanie-sten-pod-pokrasku", "t": "Шпатлевание стен под покраску: пошаговая инструкция", "i": "🎨", "c": "vnutrennyaya-otdelka"}, {"s": "shumanet-100-zvukoizolyatsiya", "t": "Шуманет 100: характеристики, монтаж и эффективность шумоизоляции", "i": "🎨", "c": "vnutrennyaya-otdelka"}, {"s": "shumoizolyatsiya-krovli-iz-profnastila", "t": "Шумоизоляция кровли из профнастила: материалы и монтаж", "i": "🌡️", "c": "uteplenie-doma"}, {"s": "shumoizolyatsiya-metallocherepitsy-iznutri-kryshi", "t": "Шумоизоляция металлочерепицы изнутри: материалы и технология", "i": "🌡️", "c": "uteplenie-doma"}, {"s": "shag-obreshetki-dlya-metallicheskogo-sajdinga", "t": "Шаг обрешетки под металлический сайдинг: нормы и монтаж", "i": "🧱", "c": "fasad-i-sajding"}, {"s": "shag-obreshetki-pod-klikfalts-na-kryshu", "t": "Шаг обрешетки под кликфальц: расчет и требования СНиП", "i": "🔨", "c": "montazh-krovli"}, {"s": "shale-krysha", "t": "Кровля шале: устройство, монтаж и выбор материалов", "i": "🏗️", "c": "vidy-krovli"}, {"s": "shumoizolyatsiya-dlya-kryshi-iz-profnastila", "t": "Шумоизоляция крыши из профнастила своими руками: материалы и монтаж", "i": "🔨", "c": "montazh-krovli"}, {"s": "shifer-kakoj-byvaet", "t": "Виды шифера: какой бывает, размеры и характеристики", "i": "🏗️", "c": "vidy-krovli"}, {"s": "shirina-parapeta", "t": "Ширина парапета: нормы, размеры и устройство узлов", "i": "🔨", "c": "montazh-krovli"}, {"s": "shtukaturka-fasada-na-uteplitel", "t": "Штукатурка фасада на утеплитель: технология мокрого фасада", "i": "🧱", "c": "fasad-i-sajding"}, {"s": "shtukaturka-s-gidroizolyatsiej", "t": "Гидроизоляционная штукатурка: виды, свойства и применение", "i": "💧", "c": "gidroizolyatsiya"}, {"s": "shumanet-otzyvy-zvukoizolyatsiya", "t": "Шуманет отзывы: реальные результаты звукоизоляции квартиры", "i": "🎨", "c": "vnutrennyaya-otdelka"}, {"s": "shablon-dlya-stropil-dvuskatnoj-kryshi", "t": "Шаблон для стропил двускатной крыши: раскрой и монтаж", "i": "📐", "c": "stropilnaya-sistema"}, {"s": "shag-obreshetki-dlya-metalloprofilya", "t": "Шаг обрешетки под металлопрофиль: таблицы и расчет", "i": "🔨", "c": "montazh-krovli"}, {"s": "shag-obreshetki-pod-klikfalts", "t": "Шаг обрешетки под кликфальц: размеры, нормы, таблица", "i": "🔨", "c": "montazh-krovli"}, {"s": "shum-ot-dozhdya-po-profnastilu-kak-izbavitsya", "t": "Как избавиться от шума дождя на крыше из профнастила", "i": "🔨", "c": "montazh-krovli"}, {"s": "shumka-kryshi", "t": "Шумоизоляция крыши: материалы, монтаж и ошибки", "i": "🌡️", "c": "uteplenie-doma"}, {"s": "shag-obreshetki-pod-shinglas", "t": "Шаг обрешетки под шинглас: таблица размеров и правила монтажа", "i": "🔨", "c": "montazh-krovli"}, {"s": "shag-samorezov-na-proflist-krysha", "t": "Шаг саморезов на профлист крыша: нормы и расчет", "i": "🔨", "c": "montazh-krovli"}, {"s": "shirina-mezhdu-stolbami-dlya-zabora", "t": "Ширина между столбами для забора: нормы и расчет", "i": "🚧", "c": "zabory-i-ograzhdeniya"}, {"s": "shirina-uteplitelya-dlya-sten", "t": "Ширина утеплителя для стен: выбор и монтаж", "i": "🌡️", "c": "uteplenie-doma"}, {"s": "shirina-kamennoj-vaty", "t": "Ширина каменной ваты: размеры, допуски и выбор", "i": "🌡️", "c": "uteplenie-doma"}, {"s": "shtukaturka-s-gidroizolyatsionnymi-svojstvami", "t": "Штукатурка с гидроизоляционными свойствами: выбор и нанесение", "i": "💧", "c": "gidroizolyatsiya"}, {"s": "shag-ferm-dlya-navesa-iz-metalloprofilya", "t": "Шаг ферм для навеса из металлопрофиля: расчет и монтаж", "i": "📐", "c": "stropilnaya-sistema"}, {"s": "shovnyj-germetik-skolko-sokhnet", "t": "Сколько сохнет шовный герметик: время для разных составов", "i": "🛠️", "c": "remont-i-ukhod"}, {"s": "shag-kontrobreshetki-pod-metallocherepitsu", "t": "Шаг контробрешетки под металлочерепицу: нормы и монтаж", "i": "🔨", "c": "montazh-krovli"}, {"s": "shag-vodostochnykh-voronok-na-skatnoj-krovle", "t": "Шаг водосточных воронок на скатной кровле: нормы и расчет", "i": "🔨", "c": "montazh-krovli"}, {"s": "shirina-metallocherepitsy-dlya-kryshi", "t": "Ширина металлочерепицы: полная и полезная, таблицы размеров", "i": "🏗️", "c": "vidy-krovli"}, {"s": "shumoizolyatsiya-vojlochnaya", "t": "Шумоизоляция войлочная: применение, свойства и монтаж", "i": "🎨", "c": "vnutrennyaya-otdelka"}, {"s": "shag-obreshetki-dlya-proflista-s21", "t": "Шаг обрешетки для профлиста С21: расчет и нормы монтажа", "i": "🔨", "c": "montazh-krovli"}, {"s": "shirina-minvaty-dlya-krovli", "t": "Ширина минваты для кровли: размеры плит и рулонов", "i": "🌡️", "c": "uteplenie-doma"}, {"s": "shtukaturka-poverkh-uteplitelya", "t": "Штукатурка по утеплителю: технология и выбор материалов", "i": "🧱", "c": "fasad-i-sajding"}, {"s": "shag-obreshetki-pod-gibkuyu-cherepitsu", "t": "Шаг обрешетки под гибкую черепицу: нормы и монтаж", "i": "🏗️", "c": "vidy-krovli"}, {"s": "shirina-bikrosta", "t": "Ширина рулона Бикроста: стандартные размеры и выбор", "i": "💧", "c": "gidroizolyatsiya"}, {"s": "shirina-mezhdu-stropilami-dvukhskatnoj-kryshi", "t": "Шаг между стропилами двухскатной крыши: расчет и нормы", "i": "📐", "c": "stropilnaya-sistema"}, {"s": "shponka-v-stroitelstve", "t": "Шпонка в строительстве: виды, назначение и применение в бетоне", "i": "🔨", "c": "montazh-krovli"}, {"s": "shumanet-100-gidro-i-kombi-raznitsa", "t": "Шуманет 100 Гидро и Комби: разница, характеристики и выбор", "i": "🌡️", "c": "uteplenie-doma"}, {"s": "shag-obreshetki-pod-cherepitsu", "t": "Шаг обрешетки под черепицу: точный расчет и монтаж", "i": "🔨", "c": "montazh-krovli"}, {"s": "shumanet-tekhnonikol", "t": "Шуманет Технониколь: характеристики, виды и монтаж", "i": "🌡️", "c": "uteplenie-doma"}, {"s": "shatrovaya-krysha-stropilnaya-sistema", "t": "Шатровая крыша: стропильная система своими руками", "i": "📐", "c": "stropilnaya-sistema"}, {"s": "shirina-metallocherepitsy-dlya-kryshi-v-chistote-i-rabochaya", "t": "Ширина металлочерепицы: габаритная и рабочая. Как не ошибиться", "i": "🏗️", "c": "vidy-krovli"}, {"s": "shumoizolyatsiya-profnastila-na-kryshe", "t": "Шумоизоляция крыши из профнастила: методы и материалы", "i": "🔨", "c": "montazh-krovli"}, {"s": "shtukaturnyj-fasad-tekhnonikol", "t": "Штукатурный фасад ТЕХНОНИКОЛЬ: технологии и монтаж", "i": "🧱", "c": "fasad-i-sajding"}, {"s": "shumoizolyatsiya-sendvich-paneli", "t": "Шумоизоляция сэндвич-панелей: методы и материалы для стен", "i": "🌡️", "c": "uteplenie-doma"}, {"s": "shifernaya-krovlya-tekhnologiya-montazha", "t": "Технология монтажа шиферной кровли: инструкция и этапы", "i": "🔨", "c": "montazh-krovli"}, {"s": "shirina-lestnitsy-dlya-chastnogo-doma-na-mansardu", "t": "Оптимальная ширина лестницы на мансарду: нормы и расчет", "i": "🎨", "c": "vnutrennyaya-otdelka"}, {"s": "shtukaturka-sten-iz-shlakobloka-snaruzhi-doma", "t": "Штукатурка стен из шлакоблока снаружи: технология и материалы", "i": "🧱", "c": "fasad-i-sajding"}, {"s": "shumoizolyatsiya-vata", "t": "Шумоизоляция ватой: выбор материала и монтаж своими руками", "i": "🎨", "c": "vnutrennyaya-otdelka"}, {"s": "shag-obreshetki-iz-profilnoj-truby-pod-profnastil", "t": "Шаг обрешетки из профильной трубы под профнастил: расчет и нормы", "i": "🔨", "c": "montazh-krovli"}, {"s": "shag-stropil-odnoskatnoj-kryshi-pod-metallocherepitsu", "t": "Шаг стропил под металлочерепицу: расчет и нормы", "i": "📐", "c": "stropilnaya-sistema"}, {"s": "shprengel-chto-eto", "t": "Шпренгель: что это такое в стропильной системе крыши", "i": "📐", "c": "stropilnaya-sistema"}, {"s": "shag-obreshetki-dvuskatnoj-kryshi", "t": "Шаг обрешетки двускатной крыши: расчет и монтаж", "i": "📐", "c": "stropilnaya-sistema"}, {"s": "shumoizolyatsiya-dlya-krovli-pod-profnastil", "t": "Шумоизоляция кровли из профнастила: материалы и монтаж", "i": "🌡️", "c": "uteplenie-doma"}, {"s": "shag-obreshetki-monterrej", "t": "Шаг обрешетки под металлочерепицу Монтеррей: размеры и схема", "i": "🔨", "c": "montazh-krovli"}, {"s": "shag-stropil-pod-osb", "t": "Шаг стропил под ОСБ: расчет и монтаж", "i": "📐", "c": "stropilnaya-sistema"}, {"s": "shag-mezhdu-fermami-dlya-navesa", "t": "Шаг между фермами для навеса: расчет, нормы и ошибки", "i": "📐", "c": "stropilnaya-sistema"}, {"s": "shatrovaya-krysha-na-pryamougolnom-dome", "t": "Шатровая крыша на прямоугольном доме: расчет и монтаж", "i": "📐", "c": "stropilnaya-sistema"}, {"s": "shifernaya-cherepitsa", "t": "Шиферная черепица: виды, монтаж и характеристики", "i": "🏗️", "c": "vidy-krovli"}, {"s": "shpatlevka-steklokholsta-pod-pokrasku", "t": "Шпатлевка стеклохолста под покраску: технология нанесения", "i": "🎨", "c": "vnutrennyaya-otdelka"}, {"s": "shpringel-eto", "t": "Шпрингель: что это в кровле, виды и монтаж", "i": "📐", "c": "stropilnaya-sistema"}, {"s": "shumoizolyatsiya-dlya-profnastila-na-kryshu", "t": "Шумоизоляция крыши из профнастила: материалы и монтаж", "i": "🔨", "c": "montazh-krovli"}, {"s": "shumanet-100-otzyvy-zvukoizolyatsiya-pod-styazhku", "t": "Шуманет-100 под стяжку: отзывы, характеристики и монтаж", "i": "🌡️", "c": "uteplenie-doma"}, {"s": "shag-obreshetki-pod-osp-dlya-myagkoj-krovli", "t": "Шаг обрешетки под ОСП для мягкой кровли: нормы и монтаж", "i": "🔨", "c": "montazh-krovli"}, {"s": "shirina-evroshtaketnika-metallicheskogo-dlya-zabora", "t": "Ширина металлического евроштакетника: выбор для забора", "i": "🚧", "c": "zabory-i-ograzhdeniya"}, {"s": "shtukaturka-ili-oboi", "t": "Что выбрать: штукатурку или обои — сравнение и советы", "i": "🎨", "c": "vnutrennyaya-otdelka"}, {"s": "shifer-iz-ondulina", "t": "Шифер из ондулина: характеристики, монтаж и отличия от аналогов", "i": "🏗️", "c": "vidy-krovli"}, {"s": "shirina-profnastila", "t": "Ширина профнастила: полная, полезная и габаритная", "i": "🧮", "c": "raschety-i-smety"}, {"s": "shtukaturka-po-kamennoj-vate", "t": "Штукатурка по каменной вате: правильный пирог и технология", "i": "🧱", "c": "fasad-i-sajding"}, {"s": "shag-obreshetki-pod-proflist-ns35", "t": "Шаг обрешетки под профнастил НС35: расчет и монтаж", "i": "🔨", "c": "montazh-krovli"}, {"s": "shirina-rulona-ruberoida", "t": "Ширина рулона рубероида: как выбрать и рассчитать", "i": "🏗️", "c": "vidy-krovli"}, {"s": "shag-obreshetki-pod-osb-12-mm-pod-myagkuyu-cherepitsu", "t": "Шаг обрешетки под ОСБ 12 мм для мягкой кровли", "i": "🔨", "c": "montazh-krovli"}, {"s": "shinglas-drakonij-zub", "t": "Мягкая кровля Шинглас Драконий зуб: характеристики и монтаж", "i": "🏗️", "c": "vidy-krovli"}, {"s": "shirina-sten-iz-kirpicha", "t": "Ширина стен из кирпича: стандарты, расчёт и нормы", "i": "📁", "c": "drugoe"}, {"s": "shtukaturka-gidroizolyatsiya", "t": "Штукатурная гидроизоляция: виды, технология нанесения и выбор", "i": "💧", "c": "gidroizolyatsiya"}, {"s": "shtukaturka-po-kamennoj-vate-tekhnologiya", "t": "Штукатурка по каменной вате: пошаговая технология монтажа", "i": "🧱", "c": "fasad-i-sajding"}, {"s": "shag-obreshetki-pod-proflist-s21-na-kryshu", "t": "Шаг обрешетки под профлист С21: нормы и расчет", "i": "🔨", "c": "montazh-krovli"}, {"s": "shag-stropilnykh-ferm", "t": "Шаг стропильных ферм: расчет, нормы и ошибки монтажа", "i": "📐", "c": "stropilnaya-sistema"}, {"s": "shelushitsya-kraska", "t": "Почему шелушится краска: причины, устранение и профилактика", "i": "🛠️", "c": "remont-i-ukhod"}, {"s": "shtukaturka-poverkh-gidroizolyatsii", "t": "Штукатурка по гидроизоляции: технология и выбор материалов", "i": "💧", "c": "gidroizolyatsiya"}, {"s": "shumoizolyatsiya-na-bitumnoj-osnove-dlya-avtomobilya", "t": "Шумоизоляция автомобиля на битумной основе: виды и монтаж", "i": "🔩", "c": "instrumenty-i-krepezh"}, {"s": "shtaketnik-olimp-premium-otzyvy", "t": "Штакетник Олимп Премиум: реальные отзывы и обзор характеристик", "i": "🚧", "c": "zabory-i-ograzhdeniya"}, {"s": "shtukaturka-mineralnoj-vaty", "t": "Мокрая штукатурка минеральной ваты: пошаговая технология", "i": "🧱", "c": "fasad-i-sajding"}, {"s": "shum-dozhdya-po-zheleznoj-kryshe", "t": "Шум дождя по железной крыше: как снизить звук и утеплить", "i": "🛠️", "c": "remont-i-ukhod"}, {"s": "shumanit-zvukoizolyatsiya", "t": "Шуманит: звукоизоляция потолка и стен своими руками", "i": "🎨", "c": "vnutrennyaya-otdelka"}, {"s": "shag-krepleniya-samorezov-dlya-proflista", "t": "Шаг крепления профлиста: схемы и нормы монтажа", "i": "📁", "c": null}, {"s": "shag-obreshetki-dlya-shifera", "t": "Шаг обрешетки под шифер: расчет и стандарты по ГОСТ", "i": "🔨", "c": "montazh-krovli"}, {"s": "shag-stropil-dlya-metallocherepitsy", "t": "Шаг стропил для металлочерепицы: расчет и нормы монтажа", "i": "📐", "c": "stropilnaya-sistema"}, {"s": "shag-stropil-pod-shifer", "t": "Шаг стропил под шифер: расчет и таблица расстояний", "i": "📐", "c": "stropilnaya-sistema"}, {"s": "shag-ferm", "t": "Шаг стропил и ферм: точные размеры и расчет", "i": "📐", "c": "stropilnaya-sistema"}, {"s": "shag-krepleniya-proflista", "t": "Шаг крепления профлиста: нормы, схемы и ошибки", "i": "🔨", "c": "montazh-krovli"}, {"s": "shatrovaya-krovlya-stropilnaya-sistema", "t": "Шатровая кровля: стропильная система, схемы и монтаж своими руками", "i": "📐", "c": "stropilnaya-sistema"}, {"s": "shirina-evroshtaketa", "t": "Ширина евроштакетника: выбор, монтаж и зазоры", "i": "🚧", "c": "zabory-i-ograzhdeniya"}, {"s": "shirina-evroshtaketnika", "t": "Ширина евроштакетника: размеры, выбор, монтаж", "i": "🚧", "c": "zabory-i-ograzhdeniya"}, {"s": "shag-cherepitsy", "t": "Шаг черепицы: как рассчитать и настроить для надежной кровли", "i": "🔨", "c": "montazh-krovli"}, {"s": "shinglas-chto-eto", "t": "Шинглас: что это такое, состав, виды и особенности монтажа", "i": "🏗️", "c": "vidy-krovli"}, {"s": "shirina-bazaltovogo-uteplitelya", "t": "Ширина базальтового утеплителя: стандарты, размеры и выбор", "i": "🌡️", "c": "uteplenie-doma"}, {"s": "shpaklevka-steklokholsta", "t": "Шпаклевка стеклохолста: полная инструкция по подготовке под покраску", "i": "🎨", "c": "vnutrennyaya-otdelka"}, {"s": "shag-fermy", "t": "Шаг фермы: расчет и монтаж стропильной системы", "i": "📐", "c": "stropilnaya-sistema"}, {"s": "shag-krepleniya-proflista-na-krovle", "t": "Шаг крепления профлиста на кровле: нормы, схемы, ошибки", "i": "🔨", "c": "montazh-krovli"}, {"s": "shag-mezhdu-obreshetkoj-pod-metallocherepitsu", "t": "Шаг обрешетки под металлочерепицу: точный расчет и монтаж", "i": "🔨", "c": "montazh-krovli"}, {"s": "shag-obreshetki-dlya-profnastila-na-kryshu", "t": "Шаг обрешетки под профнастил: нормы и расчет", "i": "🔨", "c": "montazh-krovli"}, {"s": "shag-obreshetki-dlya-metallocherepitsy-monterrej", "t": "Шаг обрешетки под металлочерепицу Монтеррей: точный расчет и монтаж", "i": "🔨", "c": "montazh-krovli"}, {"s": "shpatel-dlya-bitumnoj-mastiki", "t": "Шпатель для битумной мастики: выбор, виды и технология нанесения", "i": "💧", "c": "gidroizolyatsiya"}, {"s": "shtory-dlya-mansardy-so-skoshennym-potolkom", "t": "Шторы для мансарды: выбор и установка на скошенный потолок", "i": "🎨", "c": "vnutrennyaya-otdelka"}, {"s": "shtukaturka-mineralnoj-vaty-na-fasade", "t": "Штукатурка минеральной ваты на фасаде: технология и материалы", "i": "🌡️", "c": "uteplenie-doma"}, {"s": "shirina-evroshtaketnika-dlya-zabora", "t": "Ширина евроштакетника для забора: размеры и расчет", "i": "🚧", "c": "zabory-i-ograzhdeniya"}, {"s": "shirina-minvaty", "t": "Ширина минваты: размеры, выбор и монтаж", "i": "🌡️", "c": "uteplenie-doma"}, {"s": "shirina-proflista-dlya-kryshi-otsinkovannyj-razmery", "t": "Ширина оцинкованного профлиста для крыши: размеры и выбор", "i": "🏗️", "c": "vidy-krovli"}, {"s": "shirina-stropil-dlya-odnoskatnoj-kryshi", "t": "Ширина стропил для односкатной крыши: расчет и выбор", "i": "📐", "c": "stropilnaya-sistema"}, {"s": "shtory-na-kosoe-okno", "t": "Шторы на косое окно: выбор, крепление и установка", "i": "🎨", "c": "vnutrennyaya-otdelka"}, {"s": "shtukaturka-po-uteplitelyu", "t": "Штукатурка по утеплителю: технология мокрого фасада", "i": "🧱", "c": "fasad-i-sajding"}, {"s": "shumoizolyatsiya-potolka-tekhnonikol", "t": "Шумоизоляция потолка Технониколь: материалы и схема монтажа", "i": "🌡️", "c": "uteplenie-doma"}, {"s": "shag-krepleniya-krovelnykh-sendvich-panelej", "t": "Шаг крепления кровельных сэндвич-панелей: нормы и монтаж", "i": "🔨", "c": "montazh-krovli"}, {"s": "shirina-lestnitsy-na-mansardu-v-chastnom-dome", "t": "Ширина лестницы на мансарду: нормы и расчеты", "i": "🎨", "c": "vnutrennyaya-otdelka"}, {"s": "shtory-dlya-trapetsievidnykh-okon", "t": "Шторы для трапециевидных окон: выбор конструкции и монтаж", "i": "🎨", "c": "vnutrennyaya-otdelka"}, {"s": "shtory-na-trapetsievidnye-okna-v-derevyannom-dome", "t": "Шторы на трапециевидные окна в деревянном доме: выбор и монтаж", "i": "🎨", "c": "vnutrennyaya-otdelka"}, {"s": "shag-lag", "t": "Шаг лаг для пола: расчет и монтаж своими руками", "i": "📐", "c": "stropilnaya-sistema"}, {"s": "shag-obreshetki-pod-uteplitel-na-potolok", "t": "Шаг обрешетки под утеплитель: точный расчет и монтаж", "i": "🌡️", "c": "uteplenie-doma"}, {"s": "shirina-kirpichnoj-steny", "t": "Ширина кирпичной стены: размеры кладки, расчет и нормы", "i": "🧱", "c": "fasad-i-sajding"}, {"s": "shumoizolyatsiya-vojlokom", "t": "Шумоизоляция войлоком: свойства, монтаж и ошибки", "i": "🎨", "c": "vnutrennyaya-otdelka"}, {"s": "shag-obreshetki-pod-myagkuyu-krovlyu", "t": "Шаг обрешетки под мягкую кровлю: нормы, требования и монтаж", "i": "🔨", "c": "montazh-krovli"}, {"s": "shag-obreshetki-pod-osp", "t": "Шаг обрешетки под ОСБ: нормы, расчет и монтаж", "i": "📐", "c": "stropilnaya-sistema"}, {"s": "shirina-uteplitelya-tekhnonikol", "t": "Ширина утеплителя Технониколь: размеры, выбор и таблица", "i": "🌡️", "c": "uteplenie-doma"}, {"s": "shag-progonov-pod-proflist", "t": "Оптимальный шаг прогонов под профлист: расчет и монтаж", "i": "🔨", "c": "montazh-krovli"}, {"s": "shpilka-dlya-mauerlata-diametr", "t": "Диаметр шпильки для мауэрлата: выбор и расчет", "i": "📐", "c": "stropilnaya-sistema"}, {"s": "shumoizolyatsiya-bitumnaya", "t": "Битумная шумоизоляция авто: выбор, монтаж, эффективность", "i": "📁", "c": "drugoe"}, {"s": "shumoizolyatsionnaya-mineralnaya-vata", "t": "Шумоизоляционная минеральная вата: выбор и монтаж", "i": "🎨", "c": "vnutrennyaya-otdelka"}, {"s": "shumoizolyatsiya-kryshi-iz-proflista", "t": "Шумоизоляция крыши из профлиста: материалы и технология", "i": "🌡️", "c": "uteplenie-doma"}, {"s": "shumoizolyatsiya-pod-metallocherepitsu-na-kryshu", "t": "Шумоизоляция под металлочерепицу: материалы и технология", "i": "🔨", "c": "montazh-krovli"}, {"s": "shumoizolyatsiya-akustik-knauf", "t": "Шумоизоляция Кнауф Акустик: характеристики и монтаж своими руками", "i": "🎨", "c": "vnutrennyaya-otdelka"}, {"s": "shag-obreshetki-pod-profnastil-s-21", "t": "Шаг обрешетки под профнастил С-21: расчет и монтаж", "i": "🔨", "c": "montazh-krovli"}, {"s": "shag-obreshetki-pod-uteplitel", "t": "Шаг обрешетки под утеплитель: размеры, расчет и монтаж", "i": "🌡️", "c": "uteplenie-doma"}, {"s": "shtaketnik-eto-chto", "t": "Штакетник: что это такое, виды и размеры для забора", "i": "🚧", "c": "zabory-i-ograzhdeniya"}, {"s": "shtukaturka-po-uteplitelyu-tekhnonikol", "t": "Штукатурка по утеплителю Технониколь: технология и материалы", "i": "🧱", "c": "fasad-i-sajding"}, {"s": "shumanet-otzyvy", "t": "Шуманет отзывы: реальные плюсы, минусы и ошибки монтажа", "i": "🌡️", "c": "uteplenie-doma"}, {"s": "shag-stropil-dvuskatnoj-kryshi", "t": "Шаг стропил двускатной крыши: расчет и монтаж", "i": "📐", "c": "stropilnaya-sistema"}, {"s": "shpaklevka-i-gruntovka-sten-pod-oboi", "t": "Шпаклевка и грунтовка стен под обои: инструкция", "i": "🎨", "c": "vnutrennyaya-otdelka"}, {"s": "shinglas-minimalnyj-uklon", "t": "Минимальный уклон кровли из гибкой черепицы Шинглас", "i": "🔨", "c": "montazh-krovli"}, {"s": "shpaklevka-dlya-stykov-oboev", "t": "Шпаклевка для стыков обоев: выбор, технология и ошибки", "i": "🎨", "c": "vnutrennyaya-otdelka"}, {"s": "shpl-paneli", "t": "Шпунтованные панели для стен и потолка: монтаж, виды, выбор", "i": "🎨", "c": "vnutrennyaya-otdelka"}, {"s": "shag-krepleniya-proflista-na-krovle-samorezami", "t": "Шаг крепления профлиста на кровле саморезами: нормы и правила", "i": "🔨", "c": "montazh-krovli"}, {"s": "shag-stropilnykh-nog-dvuskatnoj-kryshi", "t": "Шаг стропильных ног двускатной крыши: расчет и монтаж", "i": "📐", "c": "stropilnaya-sistema"}, {"s": "shag-obreshetki-pod-osb", "t": "Шаг обрешетки под ОСБ для кровли: точные расчеты", "i": "📐", "c": "stropilnaya-sistema"}, {"s": "shag-stropil-na-kryshe", "t": "Шаг стропил на крыше: расчет, нормы и допустимые расстояния", "i": "📐", "c": "stropilnaya-sistema"}, {"s": "shirina-vodostochnoj-truby", "t": "Ширина водосточной трубы: как выбрать диаметр и сечение", "i": "🔨", "c": "montazh-krovli"}, {"s": "shag-obreshetki-pod-profnastil-ns35-na-kryshu", "t": "Шаг обрешетки под профнастил НС35: расчет и монтаж", "i": "🔨", "c": "montazh-krovli"}, {"s": "shtory-na-skoshennye-okna-v-mansarde", "t": "Шторы на скошенные окна в мансарде: выбор и монтаж", "i": "🎨", "c": "vnutrennyaya-otdelka"}, {"s": "shumoizolyatsiya-potolka-mineralnoj-vatoj", "t": "Шумоизоляция потолка минеральной ватой: технология и расчет", "i": "🎨", "c": "vnutrennyaya-otdelka"}, {"s": "shag-obreshetki-pod-faltsevuyu-krovlyu", "t": "Шаг обрешетки под фальцевую кровлю: нормы и расчет", "i": "🔨", "c": "montazh-krovli"}, {"s": "shinglas-raschet-krovli", "t": "Расчет кровли из шингласа: инструкция, таблицы и примеры", "i": "🧮", "c": "raschety-i-smety"}, {"s": "shirina-mezhdu-stropilami-odnoskatnoj-kryshi", "t": "Шаг стропил односкатной крыши: расчет и монтаж", "i": "📐", "c": "stropilnaya-sistema"}, {"s": "shirina-profnastila-dlya-kryshi-standart", "t": "Ширина профнастила для крыши: стандартные размеры и полезная площадь", "i": "🔨", "c": "montazh-krovli"}, {"s": "shumanet-100-analogi", "t": "Аналоги Шуманет 100: сравнение, характеристики и цены", "i": "🎨", "c": "vnutrennyaya-otdelka"}, {"s": "shag-krepleniya-vodostochnogo-zheloba", "t": "Шаг крепления водосточного желоба: нормы, расстояния и ошибки", "i": "🔨", "c": "montazh-krovli"}, {"s": "shag-stropilnoj-sistemy-dvukhskatnoj-kryshi", "t": "Шаг стропильной системы двухскатной крыши: расчет и нормы", "i": "📐", "c": "stropilnaya-sistema"}, {"s": "shirina-lista-metallocherepitsy", "t": "Ширина металлочерепицы: полная и полезная для расчета", "i": "🏗️", "c": "vidy-krovli"}, {"s": "shpaklevka-sten-pod-pokrasku-tekhnologiya", "t": "Шпаклевка стен под покраску: полная технология работ", "i": "🎨", "c": "vnutrennyaya-otdelka"}, {"s": "shumoizolyatsiya-mineralnoj-vatoj", "t": "Шумоизоляция минеральной ватой: технология и выбор материалов", "i": "🎨", "c": "vnutrennyaya-otdelka"}, {"s": "shag-obreshetki-dlya-ondulina-na-kryshu", "t": "Шаг обрешетки для Ондулина: таблица размеров и нормы", "i": "🔨", "c": "montazh-krovli"}, {"s": "shifer-volnovoj-ondulin", "t": "Шифер или ондулин: сравнение, выбор и особенности монтажа", "i": "🏗️", "c": "vidy-krovli"}, {"s": "shirina-lista-mp-20", "t": "Ширина листа профнастила МП-20: полная и полезная", "i": "🏗️", "c": "vidy-krovli"}, {"s": "shirina-stropilnoj-nogi", "t": "Ширина стропильной ноги: расчет и выбор сечения", "i": "📐", "c": "stropilnaya-sistema"}, {"s": "shpaklevka-i-gruntovka-v-chem-raznitsa", "t": "Шпаклевка и грунтовка: в чем разница и зачем нужны", "i": "🎨", "c": "vnutrennyaya-otdelka"}, {"s": "shumoizolyatsiya-minvatoj", "t": "Шумоизоляция минватой: технология и выбор материала", "i": "🎨", "c": "vnutrennyaya-otdelka"}, {"s": "shag-obreshetki-pod-profnastil-na-stenu", "t": "Шаг обрешетки под профнастил на стену: расчет и монтаж", "i": "🧱", "c": "fasad-i-sajding"}, {"s": "shifernaya-krysha-plyusy-i-minusy", "t": "Шиферная крыша: плюсы и минусы, характеристики, монтаж", "i": "🏗️", "c": "vidy-krovli"}, {"s": "shumanet-chto-eto", "t": "Шуманет: что это, виды и как выбрать изоляцию", "i": "🎨", "c": "vnutrennyaya-otdelka"}, {"s": "shifernaya-krovlya", "t": "Шиферная кровля: виды, монтаж и срок службы", "i": "🏗️", "c": "vidy-krovli"}, {"s": "shinglas-chto-eto-takoe", "t": "Шинглас: что это такое, виды и особенности монтажа гибкой черепицы", "i": "🏗️", "c": "vidy-krovli"}, {"s": "shirina-ruberoida", "t": "Ширина рубероида: размеры рулонов, ГОСТ и выбор", "i": "💧", "c": "gidroizolyatsiya"}, {"s": "shumoizolyatsiya-na-kryshu", "t": "Шумоизоляция крыши: материалы и технология монтажа", "i": "🌡️", "c": "uteplenie-doma"}, {"s": "shag-cherepitsy-obreshetki", "t": "Шаг обрешетки под черепицу: расчет и монтаж своими руками", "i": "🔨", "c": "montazh-krovli"}, {"s": "shpaklevka-po-steklokholstu", "t": "Шпаклевка по стеклохолсту: технология и выбор материалов", "i": "🎨", "c": "vnutrennyaya-otdelka"}, {"s": "shtory-dlya-kosykh-okon-v-mansarde", "t": "Шторы для косых окон в мансарде: выбор и крепление", "i": "🎨", "c": "vnutrennyaya-otdelka"}, {"s": "shtukaturka-na-uteplitel-snaruzhi", "t": "Штукатурка по утеплителю снаружи: технология мокрого фасада", "i": "🧱", "c": "fasad-i-sajding"}, {"s": "shag-ferm-dlya-navesa-iz-polikarbonata", "t": "Шаг ферм для навеса из поликарбоната: точный расчет", "i": "📐", "c": "stropilnaya-sistema"}, {"s": "shprengelnye-fermy", "t": "Шпренгельные фермы: устройство, расчет и область применения", "i": "📐", "c": "stropilnaya-sistema"}, {"s": "shag-obreshetki-dlya-proflista", "t": "Шаг обрешетки под профлист: расчет и нормы по СНиП", "i": "🔨", "c": "montazh-krovli"}, {"s": "shchel-v-zabore", "t": "Щель в заборе: как устранить зазор и укрепить ограждение", "i": "🚧", "c": "zabory-i-ograzhdeniya"}, {"s": "shpaklevka-dlya-zadelki-stykov", "t": "Шпаклевка для стыков: выбор, технология и ошибки", "i": "🎨", "c": "vnutrennyaya-otdelka"}, {"s": "shprengelnaya-sistema", "t": "Шпренгельная система: устройство, расчет и монтаж", "i": "📐", "c": "stropilnaya-sistema"}, {"s": "shirina-cherdachnoj-lestnitsy", "t": "Ширина чердачной лестницы: стандарты, нормы и расчет проема", "i": "🎨", "c": "vnutrennyaya-otdelka"}, {"s": "shumanit-izolyatsiya", "t": "Шуманит изоляция: характеристики, монтаж и отзывы", "i": "🌡️", "c": "uteplenie-doma"}, {"s": "shifer-ili-metallocherepitsa-dlya-kryshi-chto-luchshe", "t": "Шифер или металлочерепица: что лучше выбрать для крыши", "i": "🏗️", "c": "vidy-krovli"}, {"s": "shirina-paroizolyatsii-v-rulone", "t": "Ширина пароизоляции в рулоне: выбор, расчет и монтаж", "i": "💧", "c": "gidroizolyatsiya"}, {"s": "shpaklevka-shvov", "t": "Шпаклевка швов гипсокартона: пошаговая инструкция и выбор материалов", "i": "🎨", "c": "vnutrennyaya-otdelka"}, {"s": "shprengelnaya-balka", "t": "Шпренгельная балка: устройство, расчет и монтаж", "i": "📐", "c": "stropilnaya-sistema"}, {"s": "shtory-na-mansardnye-okna-so-skoshennym-potolkom-foto", "t": "Шторы на мансардные окна со скошенным потолком: виды и монтаж", "i": "🎨", "c": "vnutrennyaya-otdelka"}, {"s": "shag-obreshetki-dlya-sajdinga-vinilovogo", "t": "Шаг обрешетки под виниловый сайдинг: нормы и расчет", "i": "🧱", "c": "fasad-i-sajding"}, {"s": "shirina-uteplitelya-minvata", "t": "Ширина утеплителя минвата: таблица размеров и выбор", "i": "🌡️", "c": "uteplenie-doma"}, {"s": "shpaklevka-na-steklokholst-pod-pokrasku", "t": "Шпаклевка на стеклохолст под покраску: технология и выбор материалов", "i": "🎨", "c": "vnutrennyaya-otdelka"}, {"s": "shtory-na-okno-trapetsiej", "t": "Шторы на трапециевидное окно: виды, крепление и ошибки", "i": "🎨", "c": "vnutrennyaya-otdelka"}, {"s": "shlakovye-steny", "t": "Стены из шлакоблока: плюсы, минусы и правила кладки", "i": "📁", "c": "drugoe"}, {"s": "shurupy-dlya-terrasnoj-doski", "t": "Шурупы для террасной доски: выбор, монтаж и ошибки", "i": "🧖", "c": "banya-i-terrasa"}, {"s": "shag-obreshetki-pod-sajding", "t": "Шаг обрешетки под сайдинг: расчет и монтаж своими руками", "i": "🧱", "c": "fasad-i-sajding"}, {"s": "shag-obreshetki-pod-shifer", "t": "Шаг обрешетки под шифер: нормы, размеры и монтаж", "i": "🔨", "c": "montazh-krovli"}, {"s": "shag-obreshetki-pod-terrasnuyu-dosku", "t": "Шаг обрешетки под террасную доску: нормы и расчет", "i": "🧖", "c": "banya-i-terrasa"}, {"s": "shirina-nesushchikh-sten-v-kirpichnom-dome", "t": "Ширина несущих стен в кирпичном доме: нормы и расчеты", "i": "🧮", "c": "raschety-i-smety"}, {"s": "shpaklevka-dlya-stykov", "t": "Шпаклевка для стыков: выбор, технология и частые ошибки", "i": "🎨", "c": "vnutrennyaya-otdelka"}, {"s": "shprengelnaya-reshetka", "t": "Шпренгельная решетка стропильной системы: конструкция и монтаж", "i": "📐", "c": "stropilnaya-sistema"}, {"s": "shag-obreshetka-dlya-metallocherepitsy", "t": "Шаг обрешетки под металлочерепицу: точный расчет и монтаж", "i": "🔨", "c": "montazh-krovli"}, {"s": "shirina-volny-metallocherepitsy-dlya-kryshi", "t": "Ширина волны металлочерепицы: размеры, расчет и выбор", "i": "🏗️", "c": "vidy-krovli"}, {"s": "shumoizolyatsiya-ne-vpityvayushchaya-vlagu", "t": "Шумоизоляция, не впитывающая влагу: материалы и монтаж", "i": "🌡️", "c": "uteplenie-doma"}, {"s": "shumoizolyatsiya-tekhnonikol-dlya-pola-pod-styazhku", "t": "Шумоизоляция пола под стяжку Технониколь: выбор и монтаж", "i": "🎨", "c": "vnutrennyaya-otdelka"}, {"s": "shirina-sten-v-chastnom-dome", "t": "Ширина стен в частном доме: расчет, нормы, материалы", "i": "🧮", "c": "raschety-i-smety"}, {"s": "shirina-volny-metallocherepitsy", "t": "Ширина волны металлочерепицы: полная и полезная, размеры", "i": "🏗️", "c": "vidy-krovli"}, {"s": "shtory-na-mansardnykh-oknakh-pod-uklonom", "t": "Шторы на мансардные окна: виды и монтаж под уклоном", "i": "🎨", "c": "vnutrennyaya-otdelka"}, {"s": "shtukaturka-po-mineralovatnym-plitam", "t": "Штукатурка по минераловатным плитам: технология и материалы", "i": "🧱", "c": "fasad-i-sajding"}, {"s": "shumanet-100-otzyvy", "t": "Шуманет 100: отзывы, характеристики и особенности монтажа", "i": "🎨", "c": "vnutrennyaya-otdelka"}, {"s": "shag-progonov-dlya-proflista", "t": "Шаг прогонов для профлиста: расчет и таблица нагрузок", "i": "🔨", "c": "montazh-krovli"}, {"s": "shirina-vodostoka", "t": "Ширина водостока: выбор, расчет и монтаж системы", "i": "💧", "c": "gidroizolyatsiya"}, {"s": "shpaklevka-na-steklokholst", "t": "Шпаклевка стеклохолста под покраску: полная технология", "i": "🎨", "c": "vnutrennyaya-otdelka"}, {"s": "shtukaturka-koroed-fasadnaya-plyusy-i-minusy", "t": "Фасадная штукатурка короед: плюсы, минусы и технология", "i": "🧱", "c": "fasad-i-sajding"}, {"s": "shag-obreshetki-dlya-faltsevoj-krovli", "t": "Шаг обрешетки под фальцевую кровлю: нормы СНиП и расчет", "i": "🔨", "c": "montazh-krovli"}, {"s": "shifer-na-kryshe", "t": "Шифер на крыше: выбор, монтаж и характеристики асбоцементных листов", "i": "🏗️", "c": "vidy-krovli"}, {"s": "shirina-mezhdu-stropilami", "t": "Шаг между стропилами: нормы, расчет и монтаж", "i": "📐", "c": "stropilnaya-sistema"}, {"s": "shag-stropil-na-odnoskatnoj-kryshe", "t": "Шаг стропил на односкатной крыше: расчет и нормы", "i": "📐", "c": "stropilnaya-sistema"}, {"s": "shirina-endovy-na-krovle", "t": "Ширина ендовы на кровле: размеры, монтаж и расчет", "i": "🔨", "c": "montazh-krovli"}, {"s": "shirina-uteplitelya-dlya-sten-minvata", "t": "Ширина утеплителя для стен: выбор минваты по размеру", "i": "🌡️", "c": "uteplenie-doma"}, {"s": "shag-krepleniya-sendvich-panelej-k-metallokonstruktsiyam", "t": "Шаг крепления сэндвич панелей к металлоконструкциям: нормы и ошибки", "i": "🔩", "c": "instrumenty-i-krepezh"}, {"s": "shag-obreshetki-pod-osb-9-mm-pod-myagkuyu-krovlyu", "t": "Шаг обрешетки под ОСБ 9 мм под мягкую кровлю", "i": "🔨", "c": "montazh-krovli"}, {"s": "shag-obreshetki-pod-sajding-vinilovyj", "t": "Шаг обрешетки под виниловый сайдинг: нормы и правила", "i": "🧱", "c": "fasad-i-sajding"}, {"s": "shatrovaya-krovlya", "t": "Шатровая кровля: устройство, монтаж и расчет стропильной системы", "i": "📐", "c": "stropilnaya-sistema"}, {"s": "shokolad-krysha", "t": "Жидкая кровля ШОКОЛАД: состав, применение и ошибки монтажа", "i": "💧", "c": "gidroizolyatsiya"}, {"s": "shtukaturka-po-minvate-fasadnaya-tekhnologiya", "t": "Фасадная штукатурка по минвате: технология и пошаговая инструкция", "i": "🌡️", "c": "uteplenie-doma"}, {"s": "shumoizolyatsiya-steklovata", "t": "Шумоизоляция стекловатой: выбор, монтаж и безопасность", "i": "🌡️", "c": "uteplenie-doma"}, {"s": "shag-mezhdu-stolbami", "t": "Шаг между столбами забора: расчет и нормы монтажа", "i": "🚧", "c": "zabory-i-ograzhdeniya"}, {"s": "shumanet-100-gidro-ili-kombi-v-chem-otlichie", "t": "Шуманет 100 Гидро или Комби: в чем разница и что выбрать", "i": "🌡️", "c": "uteplenie-doma"}, {"s": "shumanit-shumoizolyatsiya", "t": "Шуманит шумоизоляция: виды, монтаж и характеристики", "i": "🎨", "c": "vnutrennyaya-otdelka"}, {"s": "shumoizolyatsiya-dlya-proflista", "t": "Шумоизоляция профлиста: материалы и монтаж своими руками", "i": "🌡️", "c": "uteplenie-doma"}, {"s": "shag-obreshetki-pod-metallocherepitsu-monterrej-pri-shirine-doski-150-mm", "t": "Шаг обрешетки под Монтеррей: схема для доски 150 мм", "i": "🔨", "c": "montazh-krovli"}, {"s": "shag-obreshetki-pod-sajding-vinilovyj-na-stenu", "t": "Шаг обрешетки под виниловый сайдинг: точные нормы и правила", "i": "🧱", "c": "fasad-i-sajding"}, {"s": "shifer-srok-sluzhby-na-kryshe", "t": "Срок службы шифера на крыше: реальные цифры и нюансы", "i": "🏗️", "c": "vidy-krovli"}, {"s": "shifernye-kryshi", "t": "Шиферные крыши: виды, расчет и монтаж своими руками", "i": "🏗️", "c": "vidy-krovli"}, {"s": "shpaklevka-i-pokraska", "t": "Шпаклевка и покраска стен своими руками: пошаговая инструкция", "i": "🎨", "c": "vnutrennyaya-otdelka"}, {"s": "shtory-dlya-mansardnogo-okna-so-skosom", "t": "Шторы для мансардного окна со скосом: виды и монтаж", "i": "🎨", "c": "vnutrennyaya-otdelka"}, {"s": "shtory-na-kosoe-okno-mansardy", "t": "Шторы на косое окно мансарды: виды, замер, монтаж", "i": "🎨", "c": "vnutrennyaya-otdelka"}, {"s": "shtory-na-mansarde-so-skoshennym-potolkom", "t": "Шторы и жалюзи на мансардные окна: выбор и монтаж", "i": "🎨", "c": "vnutrennyaya-otdelka"}, {"s": "shumoizolyatsiya-sten-tekhnonikol", "t": "Шумоизоляция стен Технониколь: выбор материалов и монтаж", "i": "🎨", "c": "vnutrennyaya-otdelka"}, {"s": "shinglas-dzhaz", "t": "Битумная черепица Shinglas Jazz: характеристики, монтаж и отзывы", "i": "🏗️", "c": "vidy-krovli"}, {"s": "shirina-mineralnoj-vaty", "t": "Ширина минеральной ваты: стандарты, выбор и монтаж", "i": "🌡️", "c": "uteplenie-doma"}, {"s": "shprengel-eto-v-stroitelstve", "t": "Шпренгель в строительстве: назначение и устройство", "i": "📐", "c": "stropilnaya-sistema"}, {"s": "shtory-na-mansardnye-okna-so-skoshennym-potolkom", "t": "Шторы на мансардные окна со скошенным потолком: выбор и монтаж", "i": "🎨", "c": "vnutrennyaya-otdelka"}, {"s": "shag-obreshetki-pod-cherepitsu-braas", "t": "Шаг обрешетки под черепицу Браас: схема и расчет", "i": "🔨", "c": "montazh-krovli"}, {"s": "shag-obreshetki-pod-metallocherepitsu-na-kryshu", "t": "Шаг обрешетки под металлочерепицу: точный расчет и монтаж", "i": "🔨", "c": "montazh-krovli"}, {"s": "shag-stropil-odnoskatnoj-kryshi", "t": "Шаг стропил односкатной крыши: расчет и монтаж", "i": "📐", "c": "stropilnaya-sistema"}, {"s": "shinglas-raschet-krovli-kalkulyator-tekhnonikol", "t": "Точный расчет кровли Шинглас в калькуляторе Технониколь", "i": "🧮", "c": "raschety-i-smety"}, {"s": "shirina-kirpichnoj-steny-zhilogo-doma", "t": "Ширина кирпичной стены: размеры для дома, СНиП и утепление", "i": "🧮", "c": "raschety-i-smety"}, {"s": "shtory-na-okno-so-skosom", "t": "Шторы на окно со скосом: выбор и монтаж карниза", "i": "🎨", "c": "vnutrennyaya-otdelka"}, {"s": "shtukaturka-na-gidroizolyatsiyu-budet-li-derzhatsya", "t": "Штукатурка на гидроизоляцию: можно ли наносить и как", "i": "💧", "c": "gidroizolyatsiya"}, {"s": "shumoizolyatsiya-pod-profnastil-na-kryshu", "t": "Шумоизоляция под профнастил на крышу: выбор материалов и монтаж", "i": "🔨", "c": "montazh-krovli"}, {"s": "shag-mezhdu-stropilami-odnoskatnoj-kryshi", "t": "Шаг между стропилами односкатной крыши: расчет и монтаж", "i": "📐", "c": "stropilnaya-sistema"}, {"s": "shag-obreshetki-pod-ondulin-na-kryshu", "t": "Шаг обрешетки под Ондулин: нормы и расчет по СНиП", "i": "🔨", "c": "montazh-krovli"}, {"s": "shpatlevka-i-pokraska-sten", "t": "Шпатлевка и покраска стен: пошаговая инструкция для дома", "i": "🎨", "c": "vnutrennyaya-otdelka"}, {"s": "shtaketnik-metallicheskij-razmery-shirina", "t": "Ширина металлического штакетника: размеры, выбор и монтаж", "i": "🚧", "c": "zabory-i-ograzhdeniya"}, {"s": "shumoizolyatsiya-s-uteplitelem", "t": "Шумоизоляция с утеплителем: выбор материалов и монтаж", "i": "🌡️", "c": "uteplenie-doma"}, {"s": "shag-obreshetki-pod-profnastil-na-kryshu-dvukhskatnuyu-s-uklonom-v-30-gradusov", "t": "Шаг обрешетки под профнастил: нормы для уклона 30 градусов", "i": "🔨", "c": "montazh-krovli"}, {"s": "shifer-plyusy-i-minusy", "t": "Шифер плюсы и минусы: анализ характеристик и свойств", "i": "🏗️", "c": "vidy-krovli"}, {"s": "shpaklevka-dlya-oboev-pod-pokrasku", "t": "Шпаклевка стен под обои под покраску: выбор и технология", "i": "🎨", "c": "vnutrennyaya-otdelka"}, {"s": "shtukaturka-na-mineralnuyu-vatu-snaruzhi", "t": "Штукатурка по минеральной вате: технология монтажа и выбор материалов", "i": "🧱", "c": "fasad-i-sajding"}, {"s": "shumoizolyatsiya-metallocherepitsy", "t": "Шумоизоляция металлочерепицы: материалы и технологии монтажа", "i": "🌡️", "c": "uteplenie-doma"}, {"s": "shtukaturka-po-minvate", "t": "Технология штукатурки по минвате: пошаговая инструкция", "i": "🌡️", "c": "uteplenie-doma"}, {"s": "shag-doski-dlya-metallocherepitsy", "t": "Шаг обрешетки под металлочерепицу: размеры и расчет", "i": "🔨", "c": "montazh-krovli"}, {"s": "shinglas-na-steny", "t": "Шинглас на стены: особенности монтажа, риски и технология", "i": "🧱", "c": "fasad-i-sajding"}, {"s": "shirina-minvaty-dlya-utepleniya-sten", "t": "Ширина минваты для утепления стен: правила выбора и монтажа", "i": "🌡️", "c": "uteplenie-doma"}, {"s": "shirina-sajdinga-dlya-naruzhnoj-otdelki", "t": "Ширина сайдинга для наружной отделки: размеры и стандарты", "i": "🧱", "c": "fasad-i-sajding"}, {"s": "shpaklevanie-steklokholsta", "t": "Шпаклевание стеклохолста: пошаговая инструкция и нюансы", "i": "🎨", "c": "vnutrennyaya-otdelka"}, {"s": "shtukaturka-na-kamennuyu-vatu", "t": "Штукатурка по каменной вате: технология мокрого фасада", "i": "🧱", "c": "fasad-i-sajding"}, {"s": "shatrovaya-krysha-stropilnaya-sistema-chertezh", "t": "Шатровая крыша: стропильная система, чертеж и монтаж, схема", "i": "📐", "c": "stropilnaya-sistema"}, {"s": "shprengelnye-balki", "t": "Шпренгельные балки: устройство, расчет и монтаж", "i": "📐", "c": "stropilnaya-sistema"}, {"s": "shprengelnye-zatyazhki", "t": "Шпренгельные затяжки: устройство, расчёт и монтаж стропильной системы", "i": "📐", "c": "stropilnaya-sistema"}, {"s": "shatrovye-krovli", "t": "Шатровая кровля: устройство, расчёт и монтаж своими руками", "i": "🏗️", "c": "vidy-krovli"}, {"s": "shpilki-dlya-krovli", "t": "Шпильки для кровли: виды, монтаж и расчет резьбовых шпилек", "i": "🔩", "c": "instrumenty-i-krepezh"}, {"s": "shprengel-v-ferme", "t": "Шпренгель в ферме: устройство, расчёт и монтаж", "i": "📐", "c": "stropilnaya-sistema"}, {"s": "shumanet-100-gidro-otzyvy", "t": "Шуманет 100 Гидро: отзывы, характеристики и применение", "i": "🌡️", "c": "uteplenie-doma"}, {"s": "shifer-ili-profnastil", "t": "Шифер или профнастил: что лучше для крыши частного дома", "i": "🏗️", "c": "vidy-krovli"}, {"s": "shtukaturka-dlya-keramzitobetonnykh-blokov", "t": "Чем штукатурить керамзитобетонные блоки внутри и снаружи", "i": "🧱", "c": "fasad-i-sajding"}, {"s": "shag-stropil-dvuskatnoj-kryshi-pod-metallocherepitsu", "t": "Шаг стропил двускатной крыши под металлочерепицу: расчет и монтаж", "i": "📐", "c": "stropilnaya-sistema"}, {"s": "shirina-cherepitsy-dlya-kryshi", "t": "Ширина черепицы для крыши: размеры, выбор и монтаж", "i": "🏗️", "c": "vidy-krovli"}, {"s": "sharniry-dlya-cherdachnoj-lestnitsy", "t": "Шарниры для чердачной лестницы: виды, выбор и ремонт", "i": "🔩", "c": "instrumenty-i-krepezh"}, {"s": "shtukaturka-po-uteplitelyu-fasada-tekhnologiya", "t": "Штукатурка по утеплителю фасада: полная технология монтажа", "i": "🌡️", "c": "uteplenie-doma"}, {"s": "shag-krepleniya-stenovykh-sendvich-panelej", "t": "Шаг крепления стеновых сэндвич-панелей: нормы и расчет", "i": "🧱", "c": "fasad-i-sajding"}, {"s": "shag-obreshetki-pod-proflist-na-kryshu", "t": "Шаг обрешетки под профлист: расчет и монтаж", "i": "🔨", "c": "montazh-krovli"}, {"s": "shirina-i-dlina-proflista-dlya-kryshi", "t": "Размеры профлиста для крыши: ширина, длина и монтаж", "i": "🏗️", "c": "vidy-krovli"}, {"s": "shumo-i-teploizolyatsiya", "t": "Шумоизоляция и теплоизоляция дома: материалы и монтаж", "i": "🌡️", "c": "uteplenie-doma"}, {"s": "shag-samorezov-na-metallocherepitsu", "t": "Шаг саморезов на металлочерепицу: нормы и схемы", "i": "🔨", "c": "montazh-krovli"}, {"s": "shifer-ili-proflist-dlya-krovli-chto-luchshe", "t": "Шифер или профлист: что лучше для кровли частного дома", "i": "🏗️", "c": "vidy-krovli"}, {"s": "shinglas-dlya-fasada", "t": "Фасадный шинглас: характеристики, выбор и правила монтажа", "i": "🧱", "c": "fasad-i-sajding"}, {"s": "shirina-mezhdu-stolbami-zabora-iz-profnastila", "t": "Ширина между столбами забора из профнастила: нормы и расчет", "i": "🚧", "c": "zabory-i-ograzhdeniya"}, {"s": "shumanet-100-chto-eto", "t": "Шуманет 100: характеристики и применение в квартире", "i": "🎨", "c": "vnutrennyaya-otdelka"}, {"s": "shag-derzhatelya-zheloba", "t": "Шаг держателя желоба: расчет и монтаж по ГОСТ", "i": "🔨", "c": "montazh-krovli"}, {"s": "shag-lag-pod-terrasnuyu-dosku-iz-listvennitsy", "t": "Шаг лаг под террасную доску из лиственницы: расчет и монтаж", "i": "🧖", "c": "banya-i-terrasa"}, {"s": "shag-stropilnykh-nog", "t": "Шаг стропильных ног: расчет, нормы СНиП, таблицы сечений", "i": "📐", "c": "stropilnaya-sistema"}, {"s": "shifer-montazh", "t": "Монтаж шифера на крышу: пошаговая инструкция и правила укладки", "i": "🔨", "c": "montazh-krovli"}, {"s": "shtukaturka-po-minplite", "t": "Штукатурка по минплите: технология мокрого фасада", "i": "🧱", "c": "fasad-i-sajding"}, {"s": "shpatlevka-po-steklokholstu", "t": "Шпатлевка по стеклохолсту: выбор, нанесение и ошибки", "i": "🎨", "c": "vnutrennyaya-otdelka"}, {"s": "shtory-na-mansardu-pod-uglom-foto", "t": "Шторы на мансарду под углом: подбор и монтаж своими руками", "i": "🎨", "c": "vnutrennyaya-otdelka"}, {"s": "shtory-na-naklonnye-okna-v-mansarde", "t": "Шторы на наклонные окна в мансарде: виды и монтаж", "i": "🎨", "c": "vnutrennyaya-otdelka"}, {"s": "shinglas-dlya-sten", "t": "Шинглас для стен: монтаж, выбор и особенности отделки", "i": "🧱", "c": "fasad-i-sajding"}, {"s": "shirina-stropil-dlya-dvuskatnoj-kryshi", "t": "Ширина стропил для двускатной крыши: расчет и выбор", "i": "📐", "c": "stropilnaya-sistema"}, {"s": "shirina-uteplitelya-dlya-krovli", "t": "Ширина утеплителя для кровли: стандарты и правила укладки", "i": "🌡️", "c": "uteplenie-doma"}, {"s": "shprengelnye-konstruktsii", "t": "Шпренгельные конструкции: устройство, расчет и монтажные хитрости", "i": "📐", "c": "stropilnaya-sistema"}, {"s": "shag-obreshetki-pod-proflist-s20", "t": "Шаг обрешетки под профлист С20: нормы и расчет", "i": "🔨", "c": "montazh-krovli"}, {"s": "shirina-sajdinga", "t": "Ширина сайдинга: таблицы размеров, выбор и монтаж", "i": "🧱", "c": "fasad-i-sajding"}, {"s": "shirina-stropil", "t": "Ширина стропил: расчет сечения и выбор доски для крыши", "i": "📐", "c": "stropilnaya-sistema"}, {"s": "shirina-uteplitelya-dlya-kryshi", "t": "Ширина утеплителя для крыши: правила выбора и монтажа", "i": "🌡️", "c": "uteplenie-doma"}, {"s": "shpaklevka-na-gidroizolyatsiyu", "t": "Шпаклевка на гидроизоляцию: выбор материалов и технология", "i": "💧", "c": "gidroizolyatsiya"}, {"s": "shtukaturka-na-uteplitel", "t": "Штукатурка по утеплителю: технология мокрого фасада", "i": "🧱", "c": "fasad-i-sajding"}, {"s": "shumoizolyatsionnaya-minvata", "t": "Шумоизоляционная минвата: выбор, монтаж и частые ошибки", "i": "🌡️", "c": "uteplenie-doma"}, {"s": "shablon-dlya-zabora-zhalyuzi", "t": "Шаблон для забора жалюзи: чертежи, размеры и инструкция", "i": "🚧", "c": "zabory-i-ograzhdeniya"}, {"s": "shag-mezhdu-fermami", "t": "Шаг между фермами: расчет, нормы и ошибки монтажа", "i": "📐", "c": "stropilnaya-sistema"}, {"s": "shag-stropilnoj-nogi", "t": "Шаг стропильной ноги: расчет, нормы и монтаж", "i": "📐", "c": "stropilnaya-sistema"}, {"s": "shtory-dlya-mansardnykh-okon-so-skoshennym-potolkom", "t": "Шторы для мансардных окон: виды и монтаж на скошенный потолок", "i": "🎨", "c": "vnutrennyaya-otdelka"}, {"s": "shpaklevka-po-steklokholstu-pod-pokrasku", "t": "Шпаклевка по стеклохолсту под покраску: пошаговая инструкция", "i": "🎨", "c": "vnutrennyaya-otdelka"}, {"s": "shtory-na-mansardu-pod-uglom", "t": "Шторы на мансарду под углом: выбор и монтаж", "i": "🎨", "c": "vnutrennyaya-otdelka"}, {"s": "shumanet-sostav", "t": "Шуманет состав: подробный разбор компонентов и их свойства", "i": "🌡️", "c": "uteplenie-doma"}, {"s": "shirina-standartnogo-proflista", "t": "Ширина стандартного профлиста: полная, рабочая и габаритная", "i": "🏗️", "c": "vidy-krovli"}, {"s": "shtukaturka-dlya-mokrogo-fasada-po-kamennoj-vate", "t": "Штукатурка для мокрого фасада по каменной вате: выбор и монтаж", "i": "🧱", "c": "fasad-i-sajding"}, {"s": "shtaketnik-pochtoj-otzyvy", "t": "Штакетник почтой: отзывы, риски доставки и советы по выбору", "i": "🚧", "c": "zabory-i-ograzhdeniya"}, {"s": "shtory-v-mansardu-s-kosym-potolkom", "t": "Шторы в мансарду с косым потолком: виды, монтаж и выбор", "i": "🎨", "c": "vnutrennyaya-otdelka"}, {"s": "shtukaturka-gidroizolyatsionnaya", "t": "Гидроизоляционная штукатурка: виды, свойства и технология нанесения", "i": "💧", "c": "gidroizolyatsiya"}, {"s": "shag-stropil-dlya-navesa", "t": "Шаг стропил для навеса: расчет, нормы и таблица", "i": "📐", "c": "stropilnaya-sistema"}, {"s": "shprengel-v-stropilnoj-sisteme-eto", "t": "Шпренгель в стропильной системе: что это и как работает", "i": "📐", "c": "stropilnaya-sistema"}, {"s": "shag-obreshetki-dlya-profnastila", "t": "Шаг обрешетки под профнастил: расчет и монтаж", "i": "🔨", "c": "montazh-krovli"}, {"s": "shag-stropil-dvuskatnoj-kryshi-pod-profnastil", "t": "Шаг стропил под профнастил: расчет, таблицы и нормы", "i": "📐", "c": "stropilnaya-sistema"}, {"s": "shpaklevka-sten-pod-oboi-eto", "t": "Шпаклевка стен под обои: выбор, технология и контроль качества", "i": "🎨", "c": "vnutrennyaya-otdelka"}, {"s": "shag-stropil-pod-profnastil-odnoskatnaya-krysha", "t": "Шаг стропил под профнастил: расчет и монтаж односкатной крыши", "i": "📐", "c": "stropilnaya-sistema"}, {"s": "shtukaturka-kamennoj-vaty-fasadnykh-sten", "t": "Штукатурка каменной ваты: технология и материалы", "i": "🧱", "c": "fasad-i-sajding"}, {"s": "shtukaturka-po-minvate-fasadnaya", "t": "Фасадная штукатурка по минвате: технология нанесения и материалы", "i": "🧱", "c": "fasad-i-sajding"}, {"s": "shumanet-100-kombi-i-gidro-otlichiya", "t": "Шуманет 100 Комби и Гидро: отличия, характеристики и применение", "i": "🌡️", "c": "uteplenie-doma"}, {"s": "shumoizolyatsiya-na-kryshu-doma-pod-profnastil", "t": "Шумоизоляция крыши под профнастил: материалы и монтаж", "i": "🌡️", "c": "uteplenie-doma"}]